hieudz/__init__.py
hieudz/core.py
hieudzbahon999-0.1.8.dist-info/LICENSE.txt
hieudzbahon999-0.1.8.dist-info/METADATA
hieudzbahon999-0.1.8.dist-info/WHEEL
hieudzbahon999-0.1.8.dist-info/top_level.txt
hieudzbahon999-0.1.8.dist-info/RECORD
