Metadata-Version: 2.1
Name: hieudzbahon999
Version: 0.1.8
Summary: A Python library with mathematical and string utilities
Home-page: https://github.com/yourusername/hieudz
Author: Your Name
Author-email: Your Name <your.email@example.com>
Classifier: Programming Language :: Python :: 3
Classifier: License :: OSI Approved :: MIT License
Classifier: Operating System :: OS Independent
Requires-Python: >=3.6
License-File: LICENSE.txt
Requires-Dist: regex>=2023.10.3
